db_claude_bridge/__about__.py
db_claude_bridge/__init__.py
db_claude_bridge/cli.py
db_claude_bridge/core.py
db_claude_bridge/exceptions.py
db_claude_bridge-0.1.1.dist-info/METADATA
db_claude_bridge-0.1.1.dist-info/WHEEL
db_claude_bridge-0.1.1.dist-info/entry_points.txt
db_claude_bridge-0.1.1.dist-info/licenses/LICENSE
db_claude_bridge-0.1.1.dist-info/RECORD
