Metadata-Version: 2.4
Name: db-claude-bridge
Version: 0.1.1
Summary: A lightweight bridge that lets the Claude Code CLI authenticate and run through Databricks Foundation Models using Databricks OAuth.
Project-URL: Homepage, https://github.com/ahdbilal/db-claude-bridge
Project-URL: Documentation, https://github.com/ahdbilal/db-claude-bridge#readme
Project-URL: Repository, https://github.com/ahdbilal/db-claude-bridge
Project-URL: Bug Tracker, https://github.com/ahdbilal/db-claude-bridge/issues
Author-email: Ahmed Bilal <ahmed.bilal@databricks.com>
License:                                  Apache License
License-File: LICENSE
Keywords: authentication,bridge,claude,claude-code-cli,databricks,foundation-models,lightweight,llm,oauth
Classifier: Development Status :: 5 - Production/Stable
Classifier: Intended Audience :: Developers
Classifier: License :: OSI Approved :: Apache Software License
Classifier: Operating System :: OS Independent
Classifier: Programming Language :: Python :: 3
Classifier: Programming Language :: Python :: 3.8
Classifier: Programming Language :: Python :: 3.9
Classifier: Programming Language :: Python :: 3.10
Classifier: Programming Language :: Python :: 3.11
Classifier: Programming Language :: Python :: 3.12
Classifier: Topic :: Internet :: WWW/HTTP :: HTTP Servers
Classifier: Topic :: Software Development :: Libraries :: Python Modules
Requires-Python: >=3.8
Requires-Dist: click>=8.0.0
Requires-Dist: pydantic>=2.0.0
Requires-Dist: python-dateutil>=2.8.0
Requires-Dist: requests>=2.25.0
Requires-Dist: typing-extensions>=4.0.0
Provides-Extra: dev
Requires-Dist: black>=23.0.0; extra == 'dev'
Requires-Dist: build>=0.10.0; extra == 'dev'
Requires-Dist: flake8>=6.0.0; extra == 'dev'
Requires-Dist: isort>=5.12.0; extra == 'dev'
Requires-Dist: mypy>=1.0.0; extra == 'dev'
Requires-Dist: pre-commit>=3.0.0; extra == 'dev'
Requires-Dist: pytest-asyncio>=0.21.0; extra == 'dev'
Requires-Dist: pytest-cov>=4.0.0; extra == 'dev'
Requires-Dist: pytest-mock>=3.10.0; extra == 'dev'
Requires-Dist: pytest>=7.0.0; extra == 'dev'
Requires-Dist: twine>=4.0.0; extra == 'dev'
Provides-Extra: docs
Requires-Dist: myst-parser>=1.0.0; extra == 'docs'
Requires-Dist: sphinx-rtd-theme>=1.2.0; extra == 'docs'
Requires-Dist: sphinx>=6.0.0; extra == 'docs'
Provides-Extra: test
Requires-Dist: pytest-asyncio>=0.21.0; extra == 'test'
Requires-Dist: pytest-cov>=4.0.0; extra == 'test'
Requires-Dist: pytest-mock>=3.10.0; extra == 'test'
Requires-Dist: pytest>=7.0.0; extra == 'test'
